biqwen-0.2.1.dist-info/METADATA
biqwen-0.2.1.dist-info/WHEEL
biqwen-0.2.1.dist-info/entry_points.txt
biqwen-0.2.1.dist-info/licenses/LICENSE
biqwen/__init__.py
biqwen/config.py
biqwen/modeling_qwen2.py
biqwen/modeling_qwen3.py
biqwen/modeling_qwen3_moe.py
biqwen-0.2.1.dist-info/RECORD
