Metadata-Version: 2.1
Name: biqwen
Version: 0.2.1
Summary: Tool for converting Qwen from uni-directional to bi-directional for tasks like classification and sentence embeddings.
Keywords: qwen,bidirectional,transformers,classification,sentence embeddings
Author-Email: clw200098 <clw200098@gmail.com>
License: MIT
Classifier: Programming Language :: Python :: 3
Classifier: License :: OSI Approved :: MIT License
Classifier: Operating System :: OS Independent
Project-URL: Homepage, https://github.com/clw8998/BiQwen
Requires-Python: >=3.8
Requires-Dist: transformers>=4.51.3
Requires-Dist: peft>=0.15.2
Requires-Dist: accelerate>=1.6.0
Requires-Dist: evaluate
Requires-Dist: seqeval
